{
  "version": 1,
  "trace_rom": "pokegold_trace.gbc",
  "trace_rom_sha256": "ECE0411C1730CD3720D1E0DC05653949ABBA2E8375800FBBA0ED1F7A86F5B040",
  "trace_symbols": "pokegold_trace.sym",
  "trace_symbols_sha256": "C9C0469A9045C15906BAFE2A334927D8A13E7E818FF51CA11885AAE17B022F8E",
  "default_watch_frames": 600,
  "default_poll_every": 1,
  "captures": [
    {
      "id": "falkner",
      "boss": "Falkner",
      "status": "FINISHED",
      "save_state": ".local/tmp/boss_state_factory/falkner_chosen_frame_4610.state",
      "out": "audit/boss_ai_trace/falkner_live.txt",
      "notes": "early-tier gym leader opener; accuracy/speed pressure; no adaptive lead",
      "stop_after_first_capture": true,
      "require_chosen_move": true
    },
    {
      "id": "bugsy",
      "boss": "Bugsy",
      "status": "FINISHED",
      "save_state": ".local/tmp/boss_state_factory/bugsy_chosen_frame_4342.state",
      "out": "audit/boss_ai_trace/bugsy_live.txt",
      "notes": "early-tier gym leader pressure; Bug/Flying role bias; no adaptive lead",
      "stop_after_first_capture": true,
      "require_chosen_move": true
    },
    {
      "id": "whitney",
      "boss": "Whitney",
      "status": "FINISHED",
      "save_state": ".local/tmp/boss_state_factory/whitney_chosen_frame_4296.state",
      "out": "audit/boss_ai_trace/whitney_live.txt",
      "notes": "early-tier gym leader pressure; normal-type tempo and setup checks; no adaptive lead",
      "stop_after_first_capture": true,
      "require_chosen_move": true
    },
    {
      "id": "morty",
      "boss": "Morty",
      "status": "FINISHED",
      "save_state": ".local/tmp/boss_state_factory/morty_chosen_frame_5466.state",
      "stop_after_first_capture": true,
      "require_chosen_move": true,
      "preflight": {
        "expect": "morty"
      },
      "out": "audit/boss_ai_trace/morty_live.txt",
      "notes": "live Morty decision after public-threat cursor fixes; chosen move observed on the current trace ROM"
    },
    {
      "id": "chuck",
      "boss": "Chuck",
      "status": "FINISHED",
      "save_state": ".local/tmp/boss_state_factory/chuck_chosen_frame_5017.state",
      "out": "audit/boss_ai_trace/chuck_live.txt",
      "notes": "mid-tier adaptive-lead gym leader; Fighting role bias and setup pressure",
      "stop_after_first_capture": true,
      "require_chosen_move": true
    },
    {
      "id": "jasmine",
      "boss": "Jasmine",
      "status": "FINISHED",
      "save_state": ".local/tmp/boss_state_factory/jasmine_chosen_frame_4520.state",
      "stop_after_first_capture": true,
      "require_chosen_move": true,
      "out": "audit/boss_ai_trace/jasmine_live.txt",
      "notes": "real Olivine Gym first decision; Magneton opener with Electric pressure, status, and screen options"
    },
    {
      "id": "pryce",
      "boss": "Pryce",
      "status": "FINISHED",
      "save_state": ".local/tmp/boss_state_factory/pryce_chosen_frame_4927.state",
      "out": "audit/boss_ai_trace/pryce_live.txt",
      "notes": "late-tier adaptive-lead gym leader; Ice/Ground role bias and weather/setup planning",
      "stop_after_first_capture": true,
      "require_chosen_move": true
    },
    {
      "id": "clair",
      "boss": "Clair",
      "status": "FINISHED",
      "save_state": ".local/tmp/boss_state_factory/clair_chosen_frame_4567.state",
      "out": "audit/boss_ai_trace/clair_live.txt",
      "notes": "first-turn Spikes; Thunder Wave fail gates; Spikes+Roar; +2 setup punish",
      "stop_after_first_capture": true,
      "require_chosen_move": true
    },
    {
      "id": "brock",
      "boss": "Brock",
      "status": "FINISHED",
      "save_state": ".local/tmp/boss_state_factory/brock_chosen_frame_4565.state",
      "out": "audit/boss_ai_trace/brock_live.txt",
      "notes": "late-tier adaptive-lead Kanto gym leader; Rock/Ground pressure and switch reasoning",
      "stop_after_first_capture": true,
      "require_chosen_move": true
    },
    {
      "id": "misty",
      "boss": "Misty",
      "status": "FINISHED",
      "save_state": ".local/tmp/boss_state_factory/misty_chosen_frame_4341.state",
      "out": "audit/boss_ai_trace/misty_live.txt",
      "notes": "late-tier adaptive-lead Kanto gym leader; Water pressure and public threat handling",
      "stop_after_first_capture": true,
      "require_chosen_move": true
    },
    {
      "id": "lt_surge",
      "boss": "Lt. Surge",
      "status": "FINISHED",
      "save_state": ".local/tmp/boss_state_factory/lt_surge_chosen_frame_4746.state",
      "out": "audit/boss_ai_trace/lt_surge_live.txt",
      "notes": "late-tier adaptive-lead Kanto gym leader; Electric pressure and immunity-aware play",
      "stop_after_first_capture": true,
      "require_chosen_move": true
    },
    {
      "id": "erika",
      "boss": "Erika",
      "status": "FINISHED",
      "save_state": ".local/tmp/boss_state_factory/erika_chosen_frame_4793.state",
      "out": "audit/boss_ai_trace/erika_live.txt",
      "notes": "late-tier adaptive-lead Kanto gym leader; Grass status/recovery pressure",
      "stop_after_first_capture": true,
      "require_chosen_move": true
    },
    {
      "id": "janine",
      "boss": "Janine",
      "status": "FINISHED",
      "save_state": ".local/tmp/boss_state_factory/janine_chosen_frame_4208.state",
      "out": "audit/boss_ai_trace/janine_live.txt",
      "notes": "late-tier adaptive-lead Kanto gym leader; Poison status fail gates and setup denial",
      "stop_after_first_capture": true,
      "require_chosen_move": true
    },
    {
      "id": "sabrina",
      "boss": "Sabrina",
      "status": "FINISHED",
      "save_state": ".local/tmp/boss_state_factory/sabrina_chosen_frame_4836.state",
      "out": "audit/boss_ai_trace/sabrina_live.txt",
      "notes": "late-tier adaptive-lead Kanto gym leader; Psychic pressure and public threat handling",
      "stop_after_first_capture": true,
      "require_chosen_move": true
    },
    {
      "id": "blaine",
      "boss": "Blaine",
      "status": "FINISHED",
      "save_state": ".local/tmp/boss_state_factory/blaine_chosen_frame_4789.state",
      "out": "audit/boss_ai_trace/blaine_live.txt",
      "notes": "late-tier adaptive-lead Kanto gym leader; Fire pressure and weather/setup reasoning",
      "stop_after_first_capture": true,
      "require_chosen_move": true
    },
    {
      "id": "blue",
      "boss": "Blue",
      "status": "FINISHED",
      "save_state": ".local/tmp/boss_state_factory/blue_chosen_frame_4971.state",
      "out": "audit/boss_ai_trace/blue_live.txt",
      "notes": "late-tier adaptive-lead Kanto gym leader; mixed-team switch and public threat reasoning",
      "stop_after_first_capture": true,
      "require_chosen_move": true
    },
    {
      "id": "koga",
      "boss": "Koga",
      "status": "FINISHED",
      "save_state": ".local/tmp/boss_state_factory/koga_chosen_frame_4835.state",
      "out": "audit/boss_ai_trace/koga_live.txt",
      "notes": "first-turn Spikes; Toxic fail gates; +2 setup Haze",
      "stop_after_first_capture": true,
      "require_chosen_move": true
    },
    {
      "id": "champion_lance",
      "boss": "Champion Lance",
      "status": "FINISHED",
      "save_state": ".local/tmp/boss_state_factory/champion_lance_chosen_frame_4970.state",
      "out": "audit/boss_ai_trace/champion_lance_live.txt",
      "notes": "non-KO Hyper Beam avoidance; Spikes+Roar; immunity pivot preference",
      "stop_after_first_capture": true,
      "require_chosen_move": true
    },
    {
      "id": "shared_switch_loop",
      "boss": "Shared switch-loop",
      "status": "FINISHED",
      "save_state": ".local/tmp/boss_state_factory/shared_switch_loop_frame_200.state",
      "out": "audit/boss_ai_trace/shared_switch_loop_live.txt",
      "notes": "synthetic Jasmine battle context; public Earthquake pressure proposes returning to the last switched-out mon; confidence 80 beats Jasmine's 74 threshold but loses to the 84 anti-loop threshold",
      "watch_frames": 180,
      "poll_every": 1,
      "stop_after_first_capture": true,
      "require_chosen_move": false
    }
  ]
}
